aiogram_cli/__init__.py
aiogram_cli/cli.py
aiogram_cli2-1.0.6.dist-info/METADATA
aiogram_cli2-1.0.6.dist-info/WHEEL
aiogram_cli2-1.0.6.dist-info/entry_points.txt
aiogram_cli2-1.0.6.dist-info/top_level.txt
aiogram_cli2-1.0.6.dist-info/RECORD
