Metadata-Version: 2.1
Name: aiogram-cli2
Version: 1.0.6
Summary: bu aiogram kutubxonasi uchun aiogram cli (command line tool)
Home-page: https://github.com/sinofarmonovzfkrvjl/aiogram-cli
Author: https://t.me/python_dev323
Classifier: Programming Language :: Python :: 3
Classifier: License :: OSI Approved :: MIT License
Classifier: Operating System :: OS Independent
Requires-Dist: watchdog
